Workbook

Sheet 表紙
O8: LMS学習管理システム
O9: 体験型Java研修
S11: 共通設計
X15: ="第"&TEXT(MAX(更新履歴!A8:I167),"#0.0")&"版" -> 第1.0版 | AA15: =MAX(更新履歴!J8:Q31) -> 44265
U18: 作成者 | Z18: 審査者 | AE18: 承認者
U19: 臼井

Sheet 更新履歴
A1: プロジェクト名 | J1: システム名 | R1: 共通設計 | AJ1: 作成者 | AO1: 作成日 | AT1: 更新者 | AY1: 更新日
A2: =表紙!O9 -> 体験型Java研修 | J2: =表紙!O8 -> LMS学習管理システム | R2: 更新履歴 | AJ2: 臼井 | AO2: 44265
A5: バージョン | J5: 日付 | R5: 章番号 | V5: 内容 | AT5: 作成者 / 更新者
A8: 1 | J8: 44265 | R8: 全て | V8: 新規作成 | AT8: 臼井

Sheet 機能一覧
A1: プロジェクト名 | K1: システム名 | U1: =表紙!S11 -> 共通設計 | AO1: 作成者 | AU1: 作成日 | BA1: 更新者 | BG1: 更新日
A2: =表紙!O9 -> 体験型Java研修 | K2: =表紙!O8 -> LMS学習管理システム | U2: 機能一覧 | AO2: 臼井 | AU2: 44265
A5: No. | C5: 機能名 | U5: 画面名 | AK5: 機能詳細/備考 | BC5: 参照可能権限
BC6: 受 | BE6: 講 | BG6: 企 | BI6: 育 | BK6: 管
A7: =MAX(A$5:INDIRECT("A"&ROW()-1))+1 -> 1 | C7: ログイン機能 | U7: ログイン画面 | AK7: システムへのログインを行う際に使用。 3回連続でログインに失敗した場合はロックする。 | BC7: 〇 | BE7: 〇 | BG7: 〇 | BI7: 〇 | BK7: 〇
A8: =MAX(A$5:INDIRECT("A"&ROW()-1))+1 -> 2 | C8: パスワード再設定機能 | U8: パスワード再設定画面 | AK8: 自分自身のパスワードの再設定を行う際に使用。 | BC8: 〇 | BE8: 〇 | BG8: 〇 | BI8: 〇 | BK8: 〇
A9: =MAX(A$5:INDIRECT("A"&ROW()-1))+1 -> 3 | U9: パスワード再設定画面 | AK9: パスワードの再設定が完了した際に表示する画面。 | BC9: 〇 | BE9: 〇 | BG9: 〇 | BI9: 〇 | BK9: 〇
A10: =MAX(A$5:INDIRECT("A"&ROW()-1))+1 -> 4 | U10: パスワード再設定画面 | AK10: パスワードの再設定時にエラーが発生した際に表示する画面。 | BC10: 〇 | BE10: 〇 | BG10: 〇 | BI10: 〇 | BK10: 〇
A11: =MAX(A$5:INDIRECT("A"&ROW()-1))+1 -> 5 | C11: 企業変更機能 | U11: 企業一覧画面 | AK11: 企業の一覧を表示する画面。 企業毎にファイル共有機能を有効/無効にするかを設定する際に使用。 | BC11: × | BE11: × | BG11: × | BI11: × | BK11: 〇
A12: =MAX(A$5:INDIRECT("A"&ROW()-1))+1 -> 6 | C12: コース登録機能 | U12: コース一覧画面 | AK12: コースの一覧を表示する画面。 | BC12: × | BE12: 〇 | BG12: × | BI12: × | BK12: 〇
A13: =MAX(A$5:INDIRECT("A"&ROW()-1))+1 -> 7 | U13: コース詳細画面 | AK13: 通常コースの詳細を表示する画面。 | BC13: 〇 | BE13: 〇 | BG13: × | BI13: × | BK13: 〇
A14: =MAX(A$5:INDIRECT("A"&ROW()-1))+1 -> 8 | U14: 通常コース登録画面 | AK14: 通常コースの登録を行う画面。 | BC14: × | BE14: × | BG14: × | BI14: × | BK14: 〇
A15: =MAX(A$5:INDIRECT("A"&ROW()-1))+1 -> 9 | U15: 通常コース登録(詳細)画面 | AK15: 通常コースのカテゴリー、セクションの登録を行う画面。 | BC15: × | BE15: × | BG15: × | BI15: × | BK15: 〇
A16: =MAX(A$5:INDIRECT("A"&ROW()-1))+1 -> 10 | U16: コース概要変更画面 | AK16: 通常コースの変更を行う画面。 | BC16: × | BE16: × | BG16: × | BI16: × | BK16: 〇
A17: =MAX(A$5:INDIRECT("A"&ROW()-1))+1 -> 11 | U17: コース変更(詳細)画面 | AK17: 通常コースのカテゴリー、セクションの変更を行う画面。 | BC17: × | BE17: × | BG17: × | BI17: × | BK17: 〇
A18: =MAX(A$5:INDIRECT("A"&ROW()-1))+1 -> 12 | U18: セクション詳細画面 | AK18: セクションの詳細を表示する画面。 試験の受験や日報、週報、月報の提出、セクションに設定された教材をダウンロードする際に使用。 | BC18: 〇 | BE18: 〇 | BG18: × | BI18: × | BK18: 〇
A19: =MAX(A$5:INDIRECT("A"&ROW()-1))+1 -> 13 | C19: 開講セット出力機能 | U19: 開講セット出力画面 | AK19: 開講セットのCSV出力を行う画面。 現在は使用していない。 | BC19: × | BE19: × | BG19: × | BI19: × | BK19: 〇
A20: =MAX(A$5:INDIRECT("A"&ROW()-1))+1 -> 14 | C20: レポートテンプレート登録機能 | U20: レポート一覧画面 | AK20: 日報、週報、月報のテンプレート一覧を表示する画面。 テンプレート削除を行う際にも使用。 | BC20: × | BE20: × | BG20: × | BI20: × | BK20: 〇
A21: =MAX(A$5:INDIRECT("A"&ROW()-1))+1 -> 15 | U21: レポートテンプレート登録画面 | AK21: 日報、週報、月報のテンプレート登録を行う画面。 | BC21: × | BE21: × | BG21: × | BI21: × | BK21: 〇
A22: =MAX(A$5:INDIRECT("A"&ROW()-1))+1 -> 16 | U22: レポートテンプレート変更画面 | AK22: 日報、週報、月報のテンプレート変更を行う画面。 | BC22: × | BE22: × | BG22: × | BI22: × | BK22: 〇
A23: =MAX(A$5:INDIRECT("A"&ROW()-1))+1 -> 17 | C23: レポート提出機能 | U23: レポート一覧画面 | AK23: 提出された日報、週報、月報の一覧を表示する画面。 | BC23: × | BE23: 〇 | BG23: 〇 | BI23: 〇 | BK23: 〇
A24: =MAX(A$5:INDIRECT("A"&ROW()-1))+1 -> 18 | U24: レポート詳細画面 | AK24: 提出された日報、週報、月報の詳細を表示する画面。 フィードバックコメントの表示、登録をする際にも使用。 | BC24: 〇 | BE24: 〇 | BG24: 〇 | BI24: 〇 | BK24: 〇
A25: =MAX(A$5:INDIRECT("A"&ROW()-1))+1 -> 19 | U25: レポート提出画面 | AK25: 日報、週報、月報の提出を行う画面。 変更を行う際にも使用。 | BC25: 〇 | BE25: 〇 | BG25: × | BI25: × | BK25: 〇
A26: =MAX(A$5:INDIRECT("A"&ROW()-1))+1 -> 20 | C26: 評価レポートテンプレート登録機能 | U26: 評価レポート一覧画面 | AK26: 評価レポートのテンプレート一覧を表示する。 評価レポートのテンプレートをコピー、削除をする際にも使用。 | BC26: × | BE26: × | BG26: × | BI26: × | BK26: 〇
A27: =MAX(A$5:INDIRECT("A"&ROW()-1))+1 -> 21 | U27: 評価レポート登録画面 | AK27: 評価レポートのテンプレート登録を行う画面。 試験データ、成果物データとの紐づけを行う。 | BC27: × | BE27: × | BG27: × | BI27: × | BK27: 〇
A28: =MAX(A$5:INDIRECT("A"&ROW()-1))+1 -> 22 | U28: 評価レポート変更画面 | AK28: 評価レポートのテンプレート変更を行う画面。 試験データ、成果物データとの紐づけを変更する。 | BC28: × | BE28: × | BG28: × | BI28: × | BK28: 〇
A29: =MAX(A$5:INDIRECT("A"&ROW()-1))+1 -> 23 | C29: 評価レポート結果登録機能 | U29: 評価レポート結果登録画面 | AK29: 評価レポートの結果登録を行う画面。 評価レポートのテンプレートに応じて登録する。 | BC29: × | BE29: 〇 | BG29: × | BI29: × | BK29: 〇
A30: =MAX(A$5:INDIRECT("A"&ROW()-1))+1 -> 24 | C30: 評価レポート採点確認機能 | U30: 評価レポート採点確認画面 | AK30: 評価レポートをCSVを用い一括出力、一括採点する際に使用。 | BC30: × | BE30: 〇 | BG30: × | BI30: × | BK30: 〇
A31: =MAX(A$5:INDIRECT("A"&ROW()-1))+1 -> 25 | C31: 評価レポート公開機能、評価レポートダウンロード機能 | U31: 評価レポート一覧画面 | AK31: 評価レポートの採点状況の確認、並びに公開を行う際に使用。 | BC31: × | BE31: × | BG31: × | BI31: × | BK31: 〇
A32: =MAX(A$5:INDIRECT("A"&ROW()-1))+1 -> 26 | C32: 試験問題登録機能 | U32: 試験カテゴリー一覧画面 | AK32: 試験カテゴリーの一覧を表示する画面。 詳細試験カテゴリーを削除をする際にも使用。 | BC32: × | BE32: × | BG32: × | BI32: × | BK32: 〇
A33: =MAX(A$5:INDIRECT("A"&ROW()-1))+1 -> 27 | U33: 試験カテゴリー登録画面 | AK33: 試験カテゴリーの登録を行う画面。 | BC33: × | BE33: × | BG33: × | BI33: × | BK33: 〇
A34: =MAX(A$5:INDIRECT("A"&ROW()-1))+1 -> 28 | U34: 試験カテゴリー変更画面 | AK34: 試験カテゴリーの変更を行う画面。 | BC34: × | BE34: × | BG34: × | BI34: × | BK34: 〇
A35: =MAX(A$5:INDIRECT("A"&ROW()-1))+1 -> 29 | U35: 詳細試験カテゴリー登録画面 | AK35: 詳細試験カテゴリー登録を行う画面。 | BC35: × | BE35: × | BG35: × | BI35: × | BK35: 〇
A36: =MAX(A$5:INDIRECT("A"&ROW()-1))+1 -> 30 | U36: 詳細試験カテゴリー変更画面 | AK36: 詳細試験カテゴリー変更を行う画面。 | BC36: × | BE36: × | BG36: × | BI36: × | BK36: 〇
A37: =MAX(A$5:INDIRECT("A"&ROW()-1))+1 -> 31 | U37: 試験登録画面 | AK37: 試験の登録を行う画面。 | BC37: × | BE37: × | BG37: × | BI37: × | BK37: 〇
A38: =MAX(A$5:INDIRECT("A"&ROW()-1))+1 -> 32 | U38: 試験問題登録画面 | AK38: 試験の問題登録を行う画面。 | BC38: × | BE38: × | BG38: × | BI38: × | BK38: 〇
A39: =MAX(A$5:INDIRECT("A"&ROW()-1))+1 -> 33 | U39: 試験内容変更画面 | AK39: 試験の内容変更を行う画面。 試験名や制限時間等を変更する際に使用。 | BC39: × | BE39: × | BG39: × | BI39: × | BK39: 〇
A40: =MAX(A$5:INDIRECT("A"&ROW()-1))+1 -> 34 | U40: 試験問題変更画面 | AK40: 試験の問題変更を行う。 試験の問題数の変更は出来ない。 | BC40: × | BE40: × | BG40: × | BI40: × | BK40: 〇
A41: =MAX(A$5:INDIRECT("A"&ROW()-1))+1 -> 35 | U41: 試験一覧画面 | AK41: 試験の一覧を表示する画面。 試験を削除する際にも使用。 | BC41: × | BE41: 〇 | BG41: 〇 | BI41: 〇 | BK41: 〇
A42: =MAX(A$5:INDIRECT("A"&ROW()-1))+1 -> 36 | U42: 試験詳細画面 | AK42: 試験の詳細を表示する画面。 | BC42: 〇 | BE42: 〇 | BG42: 〇 | BI42: 〇 | BK42: 〇
A43: =MAX(A$5:INDIRECT("A"&ROW()-1))+1 -> 37 | C43: 試験実施機能 | U43: 試験開始画面 | AK43: 試験についての内容を表示する画面。 試験を開始する際に使用。 | BC43: 〇 | BE43: × | BG43: × | BI43: × | BK43: 〇
A44: =MAX(A$5:INDIRECT("A"&ROW()-1))+1 -> 38 | U44: 試験問題画面 | AK44: 試験の問題を表示する画面。 制限時間を超えた場合は自動でサブミットされる。 | BC44: 〇 | BE44: × | BG44: × | BI44: × | BK44: 〇
A45: =MAX(A$5:INDIRECT("A"&ROW()-1))+1 -> 39 | U45: 試験回答確認画面 | AK45: 試験の回答した内容を確認する画面。 誤答の場合のみ試験の解説が表示される。 | BC45: 〇 | BE45: × | BG45: × | BI45: × | BK45: 〇
A46: =MAX(A$5:INDIRECT("A"&ROW()-1))+1 -> 40 | U46: 試験結果画面 | AK46: 試験の結果を表示する画面。 | BC46: 〇 | BE46: × | BG46: × | BI46: × | BK46: 〇
A47: =MAX(A$5:INDIRECT("A"&ROW()-1))+1 -> 41 | U47: 試験結果一覧画面 | AK47: 試験結果の一覧を表示する画面。 全試験データの平均点が表示される。 | BC47: × | BE47: 〇 | BG47: 〇 | BI47: 〇 | BK47: 〇
A48: =MAX(A$5:INDIRECT("A"&ROW()-1))+1 -> 42 | U48: 試験結果詳細画面 | AK48: 試験の受験結果を表示する画面。 | BC48: 〇 | BE48: 〇 | BG48: 〇 | BI48: 〇 | BK48: 〇
A49: =MAX(A$5:INDIRECT("A"&ROW()-1))+1 -> 43 | C49: 休暇日設定機能 | U49: 休暇日一覧画面 | AK49: 休暇日の一覧を表示する画面。 休暇日の登録、削除をする際に使用。 休暇日は全コース共通となり、休暇日に講義を設定することは出来ない。 | BC49: × | BE49: × | BG49: × | BI49: × | BK49: 〇
A50: =MAX(A$5:INDIRECT("A"&ROW()-1))+1 -> 44 | C50: お知らせ登録機能 | U50: お知らせ画面 | AK50: お知らせを表示する画面。 | BC50: × | BE50: × | BG50: × | BI50: × | BK50: 〇
A51: =MAX(A$5:INDIRECT("A"&ROW()-1))+1 -> 45 | U51: お知らせ変更画面 | AK51: お知らせの変更を行う画面。 お知らせはトップページに表示される。 | BC51: × | BE51: × | BG51: × | BI51: × | BK51: 〇
A52: =MAX(A$5:INDIRECT("A"&ROW()-1))+1 -> 46 | U52: お知らせ履歴一覧 | AK52: お知らせ履歴の一覧表示する画面。 | BC52: × | BE52: × | BG52: × | BI52: × | BK52: 〇
A53: =MAX(A$5:INDIRECT("A"&ROW()-1))+1 -> 47 | C53: 面談テンプレート登録機能 | U53: 面談テンプレートファイル一覧画面 | AK53: 面談テンプレートファイルの一覧を表示する画面。 面談テンプレートファイルを削除する際にも使用。 | BC53: × | BE53: × | BG53: × | BI53: × | BK53: 〇
A54: =MAX(A$5:INDIRECT("A"&ROW()-1))+1 -> 48 | U54: 面談テンプレート登録画面 | AK54: 面談テンプレートの登録を行う画面。 | BC54: × | BE54: × | BG54: × | BI54: × | BK54: 〇
A55: =MAX(A$5:INDIRECT("A"&ROW()-1))+1 -> 49 | U55: 面談テンプレート変更画面 | AK55: 面談テンプレートの変更を行う画面。 | BC55: × | BE55: × | BG55: × | BI55: × | BK55: 〇
A56: =MAX(A$5:INDIRECT("A"&ROW()-1))+1 -> 50 | C56: 面談記録登録機能 | U56: 面談記録登録画面 | AK56: 面談記録の登録を行う画面。 面談テンプレートファイルに応じて登録する。 | BC56: × | BE56: 〇 | BG56: × | BI56: × | BK56: 〇
A57: =MAX(A$5:INDIRECT("A"&ROW()-1))+1 -> 51 | U57: 面談記録変更画面 | AK57: 面談記録の変更を行う画面。 | BC57: × | BE57: 〇 | BG57: × | BI57: × | BK57: 〇
A58: =MAX(A$5:INDIRECT("A"&ROW()-1))+1 -> 52 | C58: 会場登録機能 | U58: 会場一覧画面 | AK58: 会場の一覧を表示する画面。 会場の削除をする際にも使用。 | BC58: × | BE58: × | BG58: × | BI58: × | BK58: 〇
A59: =MAX(A$5:INDIRECT("A"&ROW()-1))+1 -> 53 | U59: 会場登録画面 | AK59: 会場の登録を行う画面。 備考欄は「タイトル$教室名$備考」形式で入力し、「タイトル」はメール一斉送信のプレースホルダに使用。 | BC59: × | BE59: × | BG59: × | BI59: × | BK59: 〇
A60: =MAX(A$5:INDIRECT("A"&ROW()-1))+1 -> 54 | U60: 会場変更画面 | AK60: 会場の変更を行う画面。 | BC60: × | BE60: × | BG60: × | BI60: × | BK60: 〇
A61: =MAX(A$5:INDIRECT("A"&ROW()-1))+1 -> 55 | U61: 会場データインポート画面 | AK61: CSVで会場登録行う画面。 CSVフォーマットのDLをする際にも使用。 | BC61: × | BE61: × | BG61: × | BI61: × | BK61: 〇
A62: =MAX(A$5:INDIRECT("A"&ROW()-1))+1 -> 56 | C62: 改修履歴登録機能 | U62: 改修履歴一覧画面 | AK62: 改修履歴の一覧を表示する画面。 改修履歴の削除をする際にも使用。 | BC62: × | BE62: × | BG62: × | BI62: × | BK62: 〇
A63: =MAX(A$5:INDIRECT("A"&ROW()-1))+1 -> 57 | U63: 改修新規登録画面 | AK63: 改修新規登録を行う画面。 LMS保守チームが使用。 | BC63: × | BE63: × | BG63: × | BI63: × | BK63: 〇
A64: =MAX(A$5:INDIRECT("A"&ROW()-1))+1 -> 58 | U64: 改修内容変更画面 | AK64: 改修内容の変更を行う画面。 LMS保守チームが使用。 | BC64: × | BE64: × | BG64: × | BI64: × | BK64: 〇
A65: =MAX(A$5:INDIRECT("A"&ROW()-1))+1 -> 59 | C65: 利用規約同意機能 | U65: 利用規約画面 | AK65: セキュリティ規約に同意を行う画面。 内容の変更はシステム上からは出来ないためLMS保守チームが実施。 | BC65: 〇 | BE65: 〇 | BG65: 〇 | BI65: 〇 | BK65: ×
A66: =MAX(A$5:INDIRECT("A"&ROW()-1))+1 -> 60 | C66: パスワード再設定機能（企業担当者） | U66: パスワード変更画面 | AK66: パスワード変更を行う画面。 | BC66: 〇 | BE66: 〇 | BG66: 〇 | BI66: 〇 | BK66: 〇
A67: =MAX(A$5:INDIRECT("A"&ROW()-1))+1 -> 61 | U67: パスワード再発行画面 | AK67: 管理者と講師がパスワードの再発行を行う画面。 | BC67: × | BE67: 〇 | BG67: × | BI67: × | BK67: 〇
A68: =MAX(A$5:INDIRECT("A"&ROW()-1))+1 -> 62 | U68: パスワード変更画面 | AK68: メール通知後にパスワード設定を行う画面。 | BC68: 〇 | BE68: 〇 | BG68: 〇 | BI68: 〇 | BK68: 〇
A69: =MAX(A$5:INDIRECT("A"&ROW()-1))+1 -> 63 | C69: ユーザ登録機能 | U69: ユーザー詳細画面 | AK69: ユーザーの詳細を表示する画面。 | BC69: 〇 | BE69: 〇 | BG69: 〇 | BI69: 〇 | BK69: 〇
A70: =MAX(A$5:INDIRECT("A"&ROW()-1))+1 -> 64 | U70: ユーザー一覧画面 | AK70: ユーザーの一覧を表示する画面。 管理者の場合はユーザーの削除をする際にも使用。 | BC70: × | BE70: 〇 | BG70: 〇 | BI70: 〇 | BK70: 〇
A71: =MAX(A$5:INDIRECT("A"&ROW()-1))+1 -> 65 | U71: マイアカウント画面 | AK71: マイアカウントの情報を表示する画面。 | BC71: × | BE71: 〇 | BG71: 〇 | BI71: 〇 | BK71: ×
A72: =MAX(A$5:INDIRECT("A"&ROW()-1))+1 -> 66 | U72: ユーザー登録画面 | AK72: ユーザー登録のメニューを表示する画面。 | BC72: × | BE72: × | BG72: 〇 | BI72: 〇 | BK72: 〇
A73: =MAX(A$5:INDIRECT("A"&ROW()-1))+1 -> 67 | U73: ユーザー登録画面 | AK73: ユーザー登録を行う画面。 | BC73: × | BE73: × | BG73: 〇 | BI73: 〇 | BK73: 〇
A74: =MAX(A$5:INDIRECT("A"&ROW()-1))+1 -> 68 | U74: ユーザー変更画面 | AK74: ユーザー情報の変更を行う画面。 会場を変更する場合は会場アサイン登録画面、見積もり情報登録画面へ遷移。 | BC74: × | BE74: × | BG74: 〇 | BI74: × | BK74: 〇
A75: =MAX(A$5:INDIRECT("A"&ROW()-1))+1 -> 69 | C75: 動画登録機能 | U75: 動画一覧画面 | AK75: 動画のカテゴリ一覧を表示する画面。 動画カテゴリーを削除する際にも使用。 | BC75: × | BE75: × | BG75: × | BI75: × | BK75: 〇
A76: =MAX(A$5:INDIRECT("A"&ROW()-1))+1 -> 70 | U76: 動画カテゴリー登録画面 | AK76: 動画のカテゴリを登録する画面。 | BC76: × | BE76: × | BG76: × | BI76: × | BK76: 〇
A77: =MAX(A$5:INDIRECT("A"&ROW()-1))+1 -> 71 | U77: 動画カテゴリー登録画面 | AK77: 動画のカテゴリを変更する画面。 | BC77: × | BE77: × | BG77: × | BI77: × | BK77: 〇
A78: =MAX(A$5:INDIRECT("A"&ROW()-1))+1 -> 72 | U78: 動画登録画面 | AK78: 動画を登録する画面。 | BC78: × | BE78: × | BG78: × | BI78: × | BK78: 〇
A79: =MAX(A$5:INDIRECT("A"&ROW()-1))+1 -> 73 | U79: 動画登録画面 | AK79: 動画を変更する画面。 | BC79: × | BE79: × | BG79: × | BI79: × | BK79: 〇
A80: =MAX(A$5:INDIRECT("A"&ROW()-1))+1 -> 74 | U80: 動画視聴画面 | AK80: 動画一覧を表示する画面。 | BC80: 〇 | BE80: 〇 | BG80: × | BI80: × | BK80: 〇
A81: =MAX(A$5:INDIRECT("A"&ROW()-1))+1 -> 75 | C81: ヘルプ機能 | U81: ヘルプ画面 | AK81: LMSの利用マニュアルの一覧を表示する画面。 内容の変更はシステム上からは出来ないためLMS保守チームが実施。 | BC81: 〇 | BE81: 〇 | BG81: 〇 | BI81: 〇 | BK81: 〇
A82: =MAX(A$5:INDIRECT("A"&ROW()-1))+1 -> 76 | C82: 勤怠情報登録機能 | U82: 勤怠情報確認（受講生一覧）画面 | AK82: 受講生の一覧を表示する画面。 | BC82: × | BE82: 〇 | BG82: 〇 | BI82: 〇 | BK82: 〇
A83: =MAX(A$5:INDIRECT("A"&ROW()-1))+1 -> 77 | U83: 勤怠管理画面 | AK83: 受講生が勤怠時間を打刻する画面。 企業担当者、育成担当者が勤務時間を参照する際にも使用。 | BC83: 〇 | BE83: × | BG83: 〇 | BI83: 〇 | BK83: ×
A84: =MAX(A$5:INDIRECT("A"&ROW()-1))+1 -> 78 | U84: 勤怠情報直接変更画面 | AK84: 受講生が入力する受講生勤怠情報を変更する画面。 | BC84: 〇 | BE84: 〇 | BG84: × | BI84: × | BK84: 〇
A85: =MAX(A$5:INDIRECT("A"&ROW()-1))+1 -> 79 | U85: 勤怠情報変更画面 | AK85: 受講生が入力する受講生勤怠情報を変更する画面。 受講生が登録した情報を講師、管理者が確定する際に使用。 | BC85: × | BE85: 〇 | BG85: × | BI85: × | BK85: 〇
A86: =MAX(A$5:INDIRECT("A"&ROW()-1))+1 -> 80 | U86: 勤怠一括登録画面 | AK86: 受講生の勤怠を一括登録する画面。 受講生が登録した情報を講師、管理者が確定する際に使用。 | BC86: × | BE86: 〇 | BG86: × | BI86: × | BK86: 〇
A87: =MAX(A$5:INDIRECT("A"&ROW()-1))+1 -> 81 | C87: ファイル共有機能 | U87: 共有フォルダ一覧画面 | AK87: 共有フォルダの一覧を表示する画面。 | BC87: × | BE87: × | BG87: × | BI87: × | BK87: 〇
A88: =MAX(A$5:INDIRECT("A"&ROW()-1))+1 -> 82 | U88: ファイル一覧画面 | AK88: アップロードされたファイルの一覧を表示する画面。 | BC88: 〇 | BE88: 〇 | BG88: 〇 | BI88: × | BK88: 〇
A89: =MAX(A$5:INDIRECT("A"&ROW()-1))+1 -> 83 | C89: エントリ確定機能 | U89: エントリ一覧画面 | AK89: エントリ一覧を表示する画面。 営業がエントリー情報を確定する際に使用。 | BC89: × | BE89: × | BG89: × | BI89: × | BK89: 〇
A90: =MAX(A$5:INDIRECT("A"&ROW()-1))+1 -> 84 | U90: エントリー情報編集画面 | AK90: エントリーを編集する画面。 企業担当者が誤ったエントリーをした場合に使用。 | BC90: × | BE90: × | BG90: × | BI90: × | BK90: 〇
A91: =MAX(A$5:INDIRECT("A"&ROW()-1))+1 -> 85 | U91: 企業紐付け(エントリー情報確定)画面 | AK91: エントリー企業と既存の企業を紐付けする画面。 | BC91: × | BE91: × | BG91: × | BI91: × | BK91: 〇
A92: =MAX(A$5:INDIRECT("A"&ROW()-1))+1 -> 86 | U92: 企業新規登録(エントリー情報確定)画面 | AK92: エントリーの企業を新規登録する画面。 新規企業がエントリーした際に使用。 | BC92: × | BE92: × | BG92: × | BI92: × | BK92: 〇
A93: =MAX(A$5:INDIRECT("A"&ROW()-1))+1 -> 87 | U93: 企業担当者紐付け(エントリー情報確定)画面 | AK93: エントリーの企業担当者と既存の企業担当者を紐付けする画面。 | BC93: × | BE93: × | BG93: × | BI93: × | BK93: 〇
A94: =MAX(A$5:INDIRECT("A"&ROW()-1))+1 -> 88 | U94: 企業担当者新規登録(エントリー情報確定)画面 | AK94: エントリーの企業担当者を新規登録する画面。 新規企業がエントリーした際に使用。 | BC94: × | BE94: × | BG94: × | BI94: × | BK94: 〇
A95: =MAX(A$5:INDIRECT("A"&ROW()-1))+1 -> 89 | U95: コース紐付け画面 | AK95: エントリーのコースと既存のコースを紐付けする画面。 | BC95: × | BE95: × | BG95: × | BI95: × | BK95: 〇
A96: =MAX(A$5:INDIRECT("A"&ROW()-1))+1 -> 90 | U96: 会場アサイン登録画面 | AK96: エントリ企業の会場と人数を登録する画面。 | BC96: × | BE96: × | BG96: × | BI96: × | BK96: 〇
A97: =MAX(A$5:INDIRECT("A"&ROW()-1))+1 -> 91 | U97: 会場選択画面 | AK97: アサインする会場を選択する画面。 | BC97: × | BE97: × | BG97: × | BI97: × | BK97: 〇
A98: =MAX(A$5:INDIRECT("A"&ROW()-1))+1 -> 92 | U98: 見積もり情報登録画面 | AK98: エントリ企業の見積もり情報を登録する画面。 複数の会場にアサインした場合は会場毎に登録。 | BC98: × | BE98: × | BG98: × | BI98: × | BK98: 〇
A99: =MAX(A$5:INDIRECT("A"&ROW()-1))+1 -> 93 | U99: エントリー確定情報画面 | AK99: エントリ情報を表示する画面。 | BC99: × | BE99: × | BG99: × | BI99: × | BK99: 〇
A100: =MAX(A$5:INDIRECT("A"&ROW()-1))+1 -> 94 | U100: 送信メール確認画面 | AK100: メール送信をするエントリ情報を表示する画面。 送信するメールは、メールテンプレートのエントリーメールから選択。 | BC100: × | BE100: × | BG100: × | BI100: × | BK100: 〇
A101: =MAX(A$5:INDIRECT("A"&ROW()-1))+1 -> 95 | U101: メール一斉送信 | AK101: エントリ情報のメールテンプレート一覧を表示する画面。 | BC101: × | BE101: × | BG101: × | BI101: × | BK101: 〇
A102: =MAX(A$5:INDIRECT("A"&ROW()-1))+1 -> 96 | C102: 会場アサイン機能 | U102: 会場アサイン集計表画面 | AK102: 会場のアサイン数の集計を表示する画面。 | BC102: × | BE102: × | BG102: × | BI102: × | BK102: 〇
...

Sheet メッセージ一覧
A1: プロジェクト名 | J1: システム名 | R1: =表紙!S11 -> 共通設計 | AJ1: 作成者 | AO1: 作成日 | AT1: 更新者 | AY1: 更新日
A2: =表紙!O9 -> 体験型Java研修 | J2: =表紙!O8 -> LMS学習管理システム | R2: メッセージ一覧 | AJ2: 臼井 | AO2: 44265
A5: No. | C5: メッセージID | M5: メッセージ内容 | AK5: 備考 | AP5: 備考
A6: =MAX(A$5:INDIRECT("A"&ROW()-1))+1 -> 1 | C6: mail.contract.subject | M6: 【東京ITスクール】ご契約内容の送付
A7: =MAX(A$5:INDIRECT("A"&ROW()-1))+1 -> 2 | C7: mail.contract.body | M7: お世話になっております。\n\n株式会社システムシェアード\n東京ITスクール運営事務局でございます。 \n\n以下の内容で契約を締結致しました。\nご確認頂きます様お願い致します。\n\n【契約内容】\n:contract:\n\n【個人情報利用目的】\n:personal:\n\n※このメールにお心当たりがない場合はご破棄くださいますようお願い致します。\n※このメールはサーバより自動送信しておりますため、ご返信頂いてもお答えできません。\nお問い合わせは、itsup@3sss.co.jpまでお願い致します。
A8: =MAX(A$5:INDIRECT("A"&ROW()-1))+1 -> 3 | C8: mail.resetpass.subject | M8: 【LMS学習管理システム】パスワード再設定手続きのお知らせ
A9: =MAX(A$5:INDIRECT("A"&ROW()-1))+1 -> 4 | C9: mail.resetpass.body | M9: LMSをご利用いただきありがとうございます。\n\nユーザのパスワード変更を受け付けました。\n下記URLにアクセス後、新規にパスワードを設定してください。\n\n:url:\n\n※このメールにお心当たりがない場合はご破棄くださいますようお願い致します。\n※このメールはサーバより自動送信しておりますため、ご返信頂いてもお答えできません。\nお問い合わせは、itsup@3sss.co.jpまでお願い致します。
A10: =MAX(A$5:INDIRECT("A"&ROW()-1))+1 -> 5 | C10: mail.logininfo.subject | M10: 【LMS学習管理システム】ログイン情報の送付
A11: =MAX(A$5:INDIRECT("A"&ROW()-1))+1 -> 6 | C11: mail.logininfo.body | M11: LMSをご利用いただきありがとうございます。\nログイン情報を発行しました。以下の認証情報を利用してログインしてください。\n\nLMS学習管理システムURL：:url:\nログインID：:login_id:\nパスワード：:password:\n\n※このメールにお心当たりがない場合はご破棄くださいますようお願い致します。\n※このメールはサーバより自動送信しておりますため、ご返信頂いてもお答えできません。\nお問い合わせは、itsup@3sss.co.jpまでお願い致します。
A12: =MAX(A$5:INDIRECT("A"&ROW()-1))+1 -> 7 | C12: mail.mailfailed.subject | M12: 【LMS】メールの送信に失敗しています。
A13: =MAX(A$5:INDIRECT("A"&ROW()-1))+1 -> 8 | C13: mail.mailfailed.body | M13: LMSをご利用いただきありがとうございます。\n\nメールの送信に失敗しているデータがあります。\nシステム管理者にお問い合わせください。\n\nメールアドレス：:mail_address:\n件名：:subject:\n送信予約日時：:que_create_date:\n\n※このメールにお心当たりがない場合はご破棄くださいますようお願い致します。\n※このメールはサーバより自動送信しておりますため、ご返信頂いてもお答えできません。\nお問い合わせは、itsup@3sss.co.jpまでお願い致します。
A14: =MAX(A$5:INDIRECT("A"&ROW()-1))+1 -> 9 | C14: attendance.update.notice | M14: 勤怠情報の登録が完了しました。
A15: =MAX(A$5:INDIRECT("A"&ROW()-1))+1 -> 10 | C15: attendance.company.joseiKinInfoIsNotExists | M15: 対象ユーザの企業は助成金情報が未入力のため、画面を表示することができません。
A16: =MAX(A$5:INDIRECT("A"&ROW()-1))+1 -> 11 | C16: regist.complete | M16: {0}の登録が完了しました。
A17: =MAX(A$5:INDIRECT("A"&ROW()-1))+1 -> 12 | C17: update.complete | M17: {0}の更新が完了しました。
... A35: =MAX(A$5:INDIRECT("A"&ROW()-1))+1 -> 30 | C35: fileShare.fileShareFlg | M35: 貴社はファイル共有機能の使用が許可されていません。

Sheet エラーメッセージ一覧
A1: プロジェクト名 | J1: システム名 | R1: =表紙!S11 -> 共通設計 | AJ1: 作成者 | AO1: 作成日 | AT1: 更新者 | AY1: 更新日
A2: =表紙!O9 -> 体験型Java研修 | J2: =表紙!O8 -> LMS学習管理システム | R2: メッセージ一覧 | AJ2: 臼井 | AO2: 44265
A5: No. | C5: メッセージID | M5: メッセージ内容 | AK5: 備考 | AP5: 備考
A6: =MAX(A$5:INDIRECT("A"&ROW()-1))+1 -> 1 | C6: header | M6: <ul style="padding-left:0;list-style:none;">
A7: =MAX(A$5:INDIRECT("A"&ROW()-1))+1 -> 2 | C7: footer | M7: </ul>
A8: =MAX(A$5:INDIRECT("A"&ROW()-1))+1 -> 3 | C8: prefix | M8: <li><span class="help-inline error">*&nbsp;
A9: =MAX(A$5:INDIRECT("A"&ROW()-1))+1 -> 4 | C9: suffix | M9: </span></li>
A10: =MAX(A$5:INDIRECT("A"&ROW()-1))+1 -> 5 | C10: invalid | M10: {0}が不正です。
A11: =MAX(A$5:INDIRECT("A"&ROW()-1))+1 -> 6 | C11: maxlength | M11: {0}の長さが最大値({1})を超えています。
A12: =MAX(A$5:INDIRECT("A"&ROW()-1))+1 -> 7 | C12: minlength | M12: {0}の長さが最小値({1})未満です。
A13: =MAX(A$5:INDIRECT("A"&ROW()-1))+1 -> 8 | C13: maxval | M13: {0}の値が最大値({1})を超えています。
A14: =MAX(A$5:INDIRECT("A"&ROW()-1))+1 -> 9 | C14: maxvalBulk | M14: {0}：{1}が最大値({2})を超えています。
A15: =MAX(A$5:INDIRECT("A"&ROW()-1))+1 -> 10 | C15: minval | M15: {0}の値が最小値({1})未満です。
A16: =MAX(A$5:INDIRECT("A"&ROW()-1))+1 -> 11 | C16: maxbytelength | M16: {0}のバイト長が最大値({1})を超えています。
A17: =MAX(A$5:INDIRECT("A"&ROW()-1))+1 -> 12 | C17: minbytelength | M17: {0}のバイト長が最小値({1})未満です。
... A157: =MAX(A$5:INDIRECT("A"&ROW()-1))+1 -> 152 | C157: evReport.csvUpload.emptyDeliverablesResult | M157: {0}行目の{1}は提出されていません。点数を入力しないで入力してください。

Sheet エラーメッセージ一覧（入力チェック）
A1: プロジェクト名 | J1: システム名 | R1: =表紙!S11 -> 共通設計 | AJ1: 作成者 | AO1: 作成日 | AT1: 更新者 | AY1: 更新日
A2: =表紙!O9 -> 体験型Java研修 | J2: =表紙!O8 -> LMS学習管理システム | R2: メッセージ一覧 | AJ2: 臼井 | AO2: 44265
A5: No. | C5: メッセージID | M5: メッセージ内容 | AK5: 備考 | AP5: 備考
A6: =MAX(A$5:INDIRECT("A"&ROW()-1))+1 -> 1 | C6: javax.validation.constraints.NotBlank.message | M6: {0}は必須です。
A7: =MAX(A$5:INDIRECT("A"&ROW()-1))+1 -> 2 | C7: javax.validation.constraints.Size.message | M7: {0}の長さが最大値({max})を超えています。
A8: =MAX(A$5:INDIRECT("A"&ROW()-1))+1 -> 3 | C8: javax.validation.constraints.Max.message | M8: {0}の値が最大値({1})を超えています。
A9: =MAX(A$5:INDIRECT("A"&ROW()-1))+1 -> 4 | C9: javax.validation.constraints.Min.message | M9: {0}の値が最小値({1})未満です。
A10: =MAX(A$5:INDIRECT("A"&ROW()-1))+1 -> 5 | C10: pattern.outRangeNumber | M10: {0}は、半角数字で、{1}～{2}の範囲内で入力してください。
A11: =MAX(A$5:INDIRECT("A"&ROW()-1))+1 -> 6 | C11: javax.validation.constraints.Email.message | M11: {0}はメールアドレスとして不正です。
A12: =MAX(A$5:INDIRECT("A"&ROW()-1))+1 -> 7 | C12: pattern.password | M12: 「パスワード」には半角英数字のみ使用可能です。また、半角英大文字、半角英小文字、数字を含めた8～20文字を入力してください。

Sheet ラベル一覧
A1: プロジェクト名 | J1: システム名 | R1: =表紙!S11 -> 共通設計 | AJ1: 作成者 | AO1: 作成日 | AT1: 更新者 | AY1: 更新日
A2: =表紙!O9 -> 体験型Java研修 | J2: =表紙!O8 -> LMS学習管理システム | R2: ラベル一覧 | AJ2: 臼井 | AO2: 44265
A5: No. | C5: ラベルID | M5: ラベル内容 | AK5: 備考 | AP5: 備考
A6: =MAX(A$5:INDIRECT("A"&ROW()-1))+1 -> 1 | C6: user | M6: ユーザー
A7: =MAX(A$5:INDIRECT("A"&ROW()-1))+1 -> 2 | C7: lmsUser | M7: ユーザー
A8: =MAX(A$5:INDIRECT("A"&ROW()-1))+1 -> 3 | C8: company | M8: 企業
A9: =MAX(A$5:INDIRECT("A"&ROW()-1))+1 -> 4 | C9: userCompany | M9: 送信先の企業担当者
A10: =MAX(A$5:INDIRECT("A"&ROW()-1))+1 -> 5 | C10: companyData | M10: 企業データ
A11: =MAX(A$5:INDIRECT("A"&ROW()-1))+1 -> 6 | C11: place | M11: 会場
A12: =MAX(A$5:INDIRECT("A"&ROW()-1))+1 -> 7 | C12: course | M12: コース
A13: =MAX(A$5:INDIRECT("A"&ROW()-1))+1 -> 8 | C13: section | M13: セクション
A14: =MAX(A$5:INDIRECT("A"&ROW()-1))+1 -> 9 | C14: category | M14: カテゴリ
A15: =MAX(A$5:INDIRECT("A"&ROW()-1))+1 -> 10 | C15: genre | M15: 試験カテゴリ
A16: =MAX(A$5:INDIRECT("A"&ROW()-1))+1 -> 11 | C16: genre.detail | M16: 詳細試験カテゴリ
A17: =MAX(A$5:INDIRECT("A"&ROW()-1))+1 -> 12 | C17: exam | M17: 試験
... A258: =MAX(A$5:INDIRECT("A"&ROW()-1))+1 -> 253 | C258: evReport.detail.deliverablesField | M258: 成果物項目
